objdict_hephhay/__init__.py
objdict_hephhay/example.py
objdict_hephhay/util.py
objdict_hephhay-0.1.1.dist-info/LICENSE
objdict_hephhay-0.1.1.dist-info/METADATA
objdict_hephhay-0.1.1.dist-info/WHEEL
objdict_hephhay-0.1.1.dist-info/top_level.txt
objdict_hephhay-0.1.1.dist-info/RECORD
