Metadata-Version: 2.1
Name: objdict-hephhay
Version: 0.1.1
Summary: An object wrapper for dict that allows for using object type notation with dictionaries.
Author-email: Daniel Farayola <faradaydanfard@gmail.com>
License: MIT License        
Project-URL: Homepage, https://github.com/hephhay/objdict.git
Project-URL: Bug Tracker, https://github.com/hephhay/objdict.git/issues
Classifier: Programming Language :: Python :: 3
Classifier: License :: OSI Approved :: MIT License
Classifier: Operating System :: OS Independent
Requires-Python: >=3.7
License-File: LICENSE
